__init__.py
tamuwhisper.py
transcribe/__init__.py
transcribe/transcribe.py
tamuwhisper-0.1.4.dist-info/METADATA
tamuwhisper-0.1.4.dist-info/WHEEL
tamuwhisper-0.1.4.dist-info/entry_points.txt
tamuwhisper-0.1.4.dist-info/top_level.txt
tamuwhisper-0.1.4.dist-info/RECORD
