Metadata-Version: 2.4
Name: tamuwhisper
Version: 0.1.4
Summary: A Utility to Initiate the Generation of Transcripts, Subtitles, and Closed Captions
Requires-Python: >=3.12
Requires-Dist: click>=8.2.1
Requires-Dist: openai-whisper
Requires-Dist: pydub>=0.25.1
Requires-Dist: ruff>=0.12.0
Requires-Dist: tqdm>=4.67.1
